hyperhttp/__init__.py
hyperhttp/client.py
hyperhttp/connection/__init__.py
hyperhttp/connection/base.py
hyperhttp/connection/manager.py
hyperhttp/connection/pool.py
hyperhttp/errors/__init__.py
hyperhttp/errors/circuit_breaker.py
hyperhttp/errors/classifier.py
hyperhttp/errors/retry.py
hyperhttp/errors/telemetry.py
hyperhttp/protocol/__init__.py
hyperhttp/protocol/base.py
hyperhttp/protocol/http1.py
hyperhttp/protocol/http2.py
hyperhttp/protocol/utils.py
hyperhttp/utils/__init__.py
hyperhttp/utils/backoff.py
hyperhttp/utils/buffer_pool.py
hyperhttp/utils/dns_cache.py
hyperhttp-1.1.0.dist-info/licenses/LICENSE
tests/__init__.py
tests/test_client.py
tests/test_connection.py
tests/test_errors.py
tests/test_http2.py
tests/test_protocol.py
tests/test_retry.py
hyperhttp-1.1.0.dist-info/METADATA
hyperhttp-1.1.0.dist-info/WHEEL
hyperhttp-1.1.0.dist-info/top_level.txt
hyperhttp-1.1.0.dist-info/RECORD
