Metadata-Version: 2.4
Name: hyperhttp
Version: 1.1.0
Summary: A high-performance HTTP client for Python
Author: Latiful Mousom
Author-email: Latiful Mousom <latifulmousom@gmail.com>
License: MIT
Project-URL: Homepage, https://github.com/lmousom/hyperhttp
Project-URL: Bug Tracker, https://github.com/lmousom/hyperhttp/issues
Project-URL: Documentation, https://hyperhttp.readthedocs.io
Project-URL: Source Code, https://github.com/lmousom/hyperhttp
Classifier: Development Status :: 3 - Alpha
Classifier: Intended Audience :: Developers
Classifier: License :: OSI Approved :: MIT License
Classifier: Programming Language :: Python :: 3.7
Classifier: Programming Language :: Python :: 3.8
Classifier: Programming Language :: Python :: 3.9
Classifier: Programming Language :: Python :: 3.10
Classifier: Programming Language :: Python :: 3.11
Requires-Python: >=3.7
License-File: LICENSE
Requires-Dist: h2>=4.1.0
Provides-Extra: test
Requires-Dist: pytest>=7.0.0; extra == "test"
Requires-Dist: pytest-asyncio>=0.18.0; extra == "test"
Requires-Dist: pytest-cov>=3.0.0; extra == "test"
Requires-Dist: aiohttp>=3.8.0; extra == "test"
Requires-Dist: httpx>=0.23.0; extra == "test"
Requires-Dist: requests>=2.28.0; extra == "test"
Provides-Extra: dev
Requires-Dist: black>=22.3.0; extra == "dev"
Requires-Dist: isort>=5.10.0; extra == "dev"
Requires-Dist: mypy>=0.960; extra == "dev"
Requires-Dist: flake8>=4.0.0; extra == "dev"
Provides-Extra: doc
Requires-Dist: mkdocs>=1.3.0; extra == "doc"
Requires-Dist: mkdocs-material>=8.2.0; extra == "doc"
Requires-Dist: mkdocstrings>=0.24.0; extra == "doc"
Requires-Dist: mkdocstrings-python>=1.7.0; extra == "doc"
Requires-Dist: pymdown-extensions>=10.0; extra == "doc"
Requires-Dist: pygments>=2.15.0; extra == "doc"
Requires-Dist: mike>=1.1.2; extra == "doc"
Dynamic: author
Dynamic: license-file
